flask_environ.py
setup.py
Flask_Environ.egg-info/PKG-INFO
Flask_Environ.egg-info/SOURCES.txt
Flask_Environ.egg-info/dependency_links.txt
Flask_Environ.egg-info/top_level.txt