Metadata-Version: 1.0
Name: Flask-Environ
Version: 0
Summary: os.environ wrapper for flask config
Home-page: https://github.com/uniphil/flask-environ
Author: Phil Schleihauf
Author-email: uniphil@gmail.com
License: DWTFYW
Platform: UNKNOWN
